Split_Excel_Package/__init__.py
Split_Excel_Package/excel_splitter.py
Split_Excel_Package-0.0.8.dist-info/LICENSE
Split_Excel_Package-0.0.8.dist-info/METADATA
Split_Excel_Package-0.0.8.dist-info/WHEEL
Split_Excel_Package-0.0.8.dist-info/top_level.txt
Split_Excel_Package-0.0.8.dist-info/RECORD
